README.md
setup.cfg
setup.py
mynomial_probability/Binomialdistribution.py
mynomial_probability/Gaussiandistribution.py
mynomial_probability/Generaldistribution.py
mynomial_probability/__init__.py
mynomial_probability.egg-info/PKG-INFO
mynomial_probability.egg-info/SOURCES.txt
mynomial_probability.egg-info/dependency_links.txt
mynomial_probability.egg-info/not-zip-safe
mynomial_probability.egg-info/top_level.txt