Metadata-Version: 1.0
Name: mynomial-probability
Version: 0.1
Summary: Gaussian and Binomial distributions
Home-page: UNKNOWN
Author: SpecialK
Author-email: blackhole@gmail.com
License: UNKNOWN
Platform: UNKNOWN
